LICENSE
MANIFEST.in
README.md
package.json
setup.py
dash_apexcharts/DashApexcharts.py
dash_apexcharts/__init__.py
dash_apexcharts/_imports_.py
dash_apexcharts/dash_apexcharts.min.js
dash_apexcharts/dash_apexcharts.min.js.map
dash_apexcharts/metadata.json
dash_apexcharts/package-info.json
dash_apexcharts.egg-info/PKG-INFO
dash_apexcharts.egg-info/SOURCES.txt
dash_apexcharts.egg-info/dependency_links.txt
dash_apexcharts.egg-info/top_level.txt