Metadata-Version: 2.1
Name: dash-apexcharts
Version: 0.0.2
Summary: Dash wrapper for Apex Charts
Home-page: UNKNOWN
Author: Gordon North <gordon@northco.nl>
License: MIT
Platform: UNKNOWN
Classifier: Framework :: Dash
License-File: LICENSE
